{"2023-11-21-2023-11-21": [{"Influencer": "constanzanale", "Centralidad": 68.04}, {"Influencer": "malvatron87", "Centralidad": 24.02}, {"Influencer": "rafoperez1", "Centralidad": 20.12}, {"Influencer": "fedesilvaferrer", "Centralidad": 17.85}, {"Influencer": "nicooalonso1889", "Centralidad": 17.85}, {"Influencer": "RememberDorni", "Centralidad": 17.03}, {"Influencer": "kronkait1492", "Centralidad": 16.5}, {"Influencer": "agubiassi", "Centralidad": 13.19}, {"Influencer": "Juanjua07455234", "Centralidad": 13.19}, {"Influencer": "dreadmau5_", "Centralidad": 13.19}, {"Influencer": "CasaferrariDf", "Centralidad": 13.19}, {"Influencer": "TrineitorM", "Centralidad": 13.19}, {"Influencer": "leandrocuervo78", "Centralidad": 13.19}, {"Influencer": "MMartinAng", "Centralidad": 13.19}, {"Influencer": "Whewhe87223317", "Centralidad": 13.19}], "2023-11-22-2023-11-22": [{"Influencer": "PregoneroL", "Centralidad": 68.15}, {"Influencer": "dondavichook", "Centralidad": 18.25}, {"Influencer": "MariaUrrestaraz", "Centralidad": 18.25}, {"Influencer": "FTiradores", "Centralidad": 14.39}, {"Influencer": "MartinT70689136", "Centralidad": 14.39}, {"Influencer": "FabianMorosini", "Centralidad": 14.39}, {"Influencer": "javiercarp1983", "Centralidad": 14.39}, {"Influencer": "masnegociosOk", "Centralidad": 12.72}, {"Influencer": "DVickyCHV", "Centralidad": 12.3}, {"Influencer": "Vero2078NOB", "Centralidad": 12.3}, {"Influencer": "cyberpunkrabio1", "Centralidad": 12.3}, {"Influencer": "LiquidSNK85", "Centralidad": 12.3}, {"Influencer": "FernandoAAcosta", "Centralidad": 12.3}, {"Influencer": "Juli_agustin_97", "Centralidad": 12.3}, {"Influencer": "caoticfairy", "Centralidad": 12.3}], "2023-11-23-2023-11-23": [{"Influencer": "funes_clari", "Centralidad": 35.36}, {"Influencer": "ramigonzalez222", "Centralidad": 35.36}, {"Influencer": "Martava48908026", "Centralidad": 35.36}, {"Influencer": "JSchiaretti", "Centralidad": 32.27}, {"Influencer": "laserenisima", "Centralidad": 32.27}, {"Influencer": "CamineroUnico", "Centralidad": 32.27}, {"Influencer": "gobdecordoba", "Centralidad": 19.36}, {"Influencer": "ObraPublicaCBA", "Centralidad": 19.36}, {"Influencer": "MinAgriCba", "Centralidad": 19.36}, {"Influencer": "SergioBussoOK", "Centralidad": 19.36}, {"Influencer": "coninagrocba", "Centralidad": 19.36}, {"Influencer": "grafassio", "Centralidad": 17.68}, {"Influencer": "marcelarivilli", "Centralidad": 17.68}, {"Influencer": "bprgustavo", "Centralidad": 17.68}, {"Influencer": "lilianalamala", "Centralidad": 17.68}], "2023-11-24-2023-11-24": [{"Influencer": "AnPasserini", "Centralidad": 44.0}, {"Influencer": "SergioMassa", "Centralidad": 39.07}, {"Influencer": "JuanjoBahillo", "Centralidad": 39.07}, {"Influencer": "vlog_koi", "Centralidad": 23.03}, {"Influencer": "Predicador30", "Centralidad": 23.03}, {"Influencer": "Hetitor7", "Centralidad": 23.03}, {"Influencer": "Nachocar1974", "Centralidad": 23.03}, {"Influencer": "tyler_durden_4", "Centralidad": 23.03}, {"Influencer": "marygrec", "Centralidad": 23.03}, {"Influencer": "wasp750", "Centralidad": 23.03}, {"Influencer": "luciaemiliaflor", "Centralidad": 23.03}, {"Influencer": "DanielR63338825", "Centralidad": 23.03}, {"Influencer": "matiaslongoni", "Centralidad": 8.93}, {"Influencer": "BichosdeCampo", "Centralidad": 8.93}, {"Influencer": "Orangelus", "Centralidad": 8.3}], "2023-11-25-2023-11-25": [{"Influencer": "AnPasserini", "Centralidad": 42.42}, {"Influencer": "SergioMassa", "Centralidad": 38.69}, {"Influencer": "JuanjoBahillo", "Centralidad": 38.69}, {"Influencer": "FernanFlodas", "Centralidad": 31.31}, {"Influencer": "hernan_zeta", "Centralidad": 31.31}, {"Influencer": "CadwellSaxon", "Centralidad": 24.82}, {"Influencer": "Juan_Parodi", "Centralidad": 24.82}, {"Influencer": "asbajolamanga00", "Centralidad": 24.82}, {"Influencer": "Lmas94230039", "Centralidad": 24.82}, {"Influencer": "ignacio12453102", "Centralidad": 24.82}, {"Influencer": "rrmorocha", "Centralidad": 9.18}, {"Influencer": "LeopoldoAndre18", "Centralidad": 8.79}, {"Influencer": "matiaslongoni", "Centralidad": 1.9}, {"Influencer": "YoSoySantaAnna", "Centralidad": 0.01}, {"Influencer": "NoticiasCaracol", "Centralidad": 0.0}], "2023-11-26-2023-11-26": [{"Influencer": "YoSoySantaAnna", "Centralidad": 70.71}, {"Influencer": "HaffelyGalarza3", "Centralidad": 16.67}, {"Influencer": "El__Balsero", "Centralidad": 16.67}, {"Influencer": "JeanCastna", "Centralidad": 16.67}, {"Influencer": "latinus_us", "Centralidad": 16.67}, {"Influencer": "lic_rogelio_jur", "Centralidad": 16.67}, {"Influencer": "Angela_FriasA", "Centralidad": 16.67}, {"Influencer": "netomnvz", "Centralidad": 16.67}, {"Influencer": "GiuIianoDMedici", "Centralidad": 16.67}, {"Influencer": "GralVictoria", "Centralidad": 16.67}, {"Influencer": "YUaemex", "Centralidad": 16.67}, {"Influencer": "ChapoyPati", "Centralidad": 16.67}, {"Influencer": "DanteZanella", "Centralidad": 16.67}, {"Influencer": "EsdeProfugos", "Centralidad": 16.67}, {"Influencer": "iRayoKrueger", "Centralidad": 16.67}], "2023-11-27-2023-11-27": [{"Influencer": "KotoBloodwell", "Centralidad": 68.15}, {"Influencer": "DianitaOtalvaro", "Centralidad": 15.96}, {"Influencer": "AlejandroDM510", "Centralidad": 14.77}, {"Influencer": "felipec27693914", "Centralidad": 14.77}, {"Influencer": "LealSredna", "Centralidad": 14.37}, {"Influencer": "Maxidky2", "Centralidad": 14.37}, {"Influencer": "ANDONELA", "Centralidad": 14.32}, {"Influencer": "luisfer646", "Centralidad": 13.93}, {"Influencer": "G413V3", "Centralidad": 13.84}, {"Influencer": "jhonsotelo", "Centralidad": 13.58}, {"Influencer": "Johan1132586", "Centralidad": 12.02}, {"Influencer": "moyavegito1927", "Centralidad": 12.01}, {"Influencer": "ArcangelFragoso", "Centralidad": 11.6}, {"Influencer": "ManuelM18131998", "Centralidad": 11.6}, {"Influencer": "architerco", "Centralidad": 11.28}], "2023-11-28-2023-11-28": [{"Influencer": "JorRausch", "Centralidad": 55.73}, {"Influencer": "Piru_laura", "Centralidad": 55.73}, {"Influencer": "Atilra_GR", "Centralidad": 43.52}, {"Influencer": "laserenisima", "Centralidad": 43.52}, {"Influencer": "bicicareta", "Centralidad": 0.0}, {"Influencer": "javierlanari", "Centralidad": 0.0}, {"Influencer": "Yolanda_Diaz_", "Centralidad": 0.0}, {"Influencer": "pedromarco3", "Centralidad": 0.0}, {"Influencer": "Carlos009776224", "Centralidad": 0.0}, {"Influencer": "KotoBloodwell", "Centralidad": 0.0}, {"Influencer": "Sant_2222", "Centralidad": 0.0}, {"Influencer": "virtualdiva01", "Centralidad": 0.0}, {"Influencer": "chismecitook", "Centralidad": 0.0}, {"Influencer": "enmichada", "Centralidad": 0.0}, {"Influencer": "MartnGo22095516", "Centralidad": 0.0}]}