{"2023-12-12-2023-12-12": {"ARG - DANONE - PROYECTO DE LEY DE REGULACIÓN DE COMERCIALIZACIÓN DE SUCEDÁNEOS DE LECHE MATERNA": [], "ARG - DANONE - LACTEOS Y PRODUCTOS DE ORIGEN VEGETAL \n": [{"valor": 1, "palabra": "tiktoker-descubrió-ingredientes"}, {"valor": 1, "palabra": "descubrió-ingredientes-danonino"}, {"valor": 1, "palabra": "ingredientes-danonino-ocurrió"}, {"valor": 1, "palabra": "danonino-ocurrió-lógica"}, {"valor": 1, "palabra": "ocurrió-lógica-preparar"}, {"valor": 1, "palabra": "lógica-preparar-quesadillas"}, {"valor": 1, "palabra": "preparar-quesadillas-segundo"}, {"valor": 1, "palabra": "quesadillas-segundo-parece"}, {"valor": 1, "palabra": "segundo-parece-alimentos"}, {"valor": 1, "palabra": "parece-alimentos-ayudarán"}, {"valor": 1, "palabra": "alimentos-ayudarán-mejorar"}, {"valor": 1, "palabra": "ayudarán-mejorar-intestinal"}, {"valor": 1, "palabra": "mejorar-intestinal-además"}, {"valor": 1, "palabra": "intestinal-además-tienen"}, {"valor": 1, "palabra": "además-tienen-probióticos"}, {"valor": 1, "palabra": "tienen-probióticos-adicione"}, {"valor": 1, "palabra": "probióticos-adicione-arepas"}, {"valor": 1, "palabra": "adicione-arepas-pésimos"}, {"valor": 1, "palabra": "arepas-pésimos-petristes"}], "ARG - DANONE - PRECIOS": [{"valor": 3, "palabra": "descubre-descuentos-irresistibles"}, {"valor": 3, "palabra": "descuentos-irresistibles-fórmula"}, {"valor": 3, "palabra": "irresistibles-fórmula-comida"}, {"valor": 3, "palabra": "fórmula-comida-nestlé"}, {"valor": 3, "palabra": "comida-nestlé-calidad"}, {"valor": 3, "palabra": "nestlé-calidad-premium"}, {"valor": 3, "palabra": "calidad-premium-precio"}, {"valor": 3, "palabra": "premium-precio-pequeño"}, {"valor": 3, "palabra": "consigue-cabello-sueños"}, {"valor": 3, "palabra": "cabello-sueños-oferta"}, {"valor": 3, "palabra": "sueños-oferta-increíble"}, {"valor": 3, "palabra": "oferta-increíble-mascarilla"}, {"valor": 3, "palabra": "increíble-mascarilla-precio"}, {"valor": 3, "palabra": "mascarilla-precio-imbatible"}, {"valor": 2, "palabra": "precios-productos-lácteos"}, {"valor": 2, "palabra": "precio-pequeño-descubre"}, {"valor": 2, "palabra": "pequeño-descubre-descuentos"}, {"valor": 2, "palabra": "lindor-bombones-chocolate"}, {"valor": 2, "palabra": "bombones-chocolate-lindor"}, {"valor": 2, "palabra": "precio-imbatible-consigue"}, {"valor": 2, "palabra": "imbatible-consigue-cabello"}, {"valor": 1, "palabra": "imagínate-naftas-comprarlas"}, {"valor": 1, "palabra": "naftas-comprarlas-gobierno"}, {"valor": 1, "palabra": "comprarlas-gobierno-derecha"}, {"valor": 1, "palabra": "gobierno-derecha-mantiene"}, {"valor": 1, "palabra": "derecha-mantiene-precios"}, {"valor": 1, "palabra": "mantiene-precios-máximos"}, {"valor": 1, "palabra": "precios-máximos-rubros"}, {"valor": 1, "palabra": "máximos-rubros-transporte"}, {"valor": 1, "palabra": "rubros-transporte-muchos"}], "ARG - DANONE - LACTEOS Y PRODUCTOS DE ORIGEN VEGETAL - MENCIONES A MARCAS": [{"valor": 2, "palabra": "precios-arriba-internacionales"}, {"valor": 2, "palabra": "entraste-hablar-política"}, {"valor": 1, "palabra": "chingar-porque-julian"}, {"valor": 1, "palabra": "porque-julian-tanque"}, {"valor": 1, "palabra": "julian-tanque-serenisima"}, {"valor": 1, "palabra": "tanque-serenisima-cuánto"}, {"valor": 1, "palabra": "serenisima-cuánto-cindor"}, {"valor": 1, "palabra": "cuánto-cindor-concha"}, {"valor": 1, "palabra": "cindor-concha-stalkeandome"}, {"valor": 1, "palabra": "concha-stalkeandome-faltaba"}, {"valor": 1, "palabra": "stalkeandome-faltaba-gallinero"}, {"valor": 1, "palabra": "faltaba-gallinero-serenísima"}, {"valor": 1, "palabra": "gallinero-serenísima-mercado"}, {"valor": 1, "palabra": "serenísima-mercado-alimentos"}, {"valor": 1, "palabra": "mercado-alimentos-clásico"}, {"valor": 1, "palabra": "alimentos-clásico-autorizo"}, {"valor": 1, "palabra": "clásico-autorizo-quilmes"}, {"valor": 1, "palabra": "autorizo-quilmes-etiquetas"}, {"valor": 1, "palabra": "quilmes-etiquetas-cerveza"}, {"valor": 1, "palabra": "etiquetas-cerveza-autorizo"}, {"valor": 1, "palabra": "cerveza-autorizo-serenisima"}, {"valor": 1, "palabra": "autorizo-serenisima-partir"}, {"valor": 1, "palabra": "serenisima-partir-empezaron"}, {"valor": 1, "palabra": "partir-empezaron-actimel"}, {"valor": 1, "palabra": "empezaron-actimel-acosta"}, {"valor": 1, "palabra": "actimel-acosta-puerta"}, {"valor": 1, "palabra": "acosta-puerta-productores"}, {"valor": 1, "palabra": "puerta-productores-inglés"}, {"valor": 1, "palabra": "productores-inglés-quiero"}, {"valor": 1, "palabra": "inglés-quiero-nominar"}], "ARG - DANONE - ABASTECIMIENTO EN SUPERMERCADOS": [{"valor": 1, "palabra": "pajita-despues-handshake"}, {"valor": 1, "palabra": "despues-handshake-amistad"}, {"valor": 1, "palabra": "handshake-amistad-sangre"}, {"valor": 1, "palabra": "amistad-sangre-cuántos"}, {"valor": 1, "palabra": "sangre-cuántos-calculas"}, {"valor": 1, "palabra": "cuántos-calculas-mañana"}, {"valor": 1, "palabra": "calculas-mañana-sabemos"}, {"valor": 1, "palabra": "mañana-sabemos-verdad"}, {"valor": 1, "palabra": "sabemos-verdad-saqueo"}, {"valor": 1, "palabra": "verdad-saqueo-únicos"}, {"valor": 1, "palabra": "saqueo-únicos-beneficiados"}, {"valor": 1, "palabra": "únicos-beneficiados-exportadores"}, {"valor": 1, "palabra": "beneficiados-exportadores-mañana"}, {"valor": 1, "palabra": "exportadores-mañana-encuentran"}, {"valor": 1, "palabra": "mañana-encuentran-supermercados"}, {"valor": 1, "palabra": "encuentran-supermercados-desabastecimiento"}, {"valor": 1, "palabra": "supermercados-desabastecimiento-perversos"}, {"valor": 1, "palabra": "desabastecimiento-perversos-además"}, {"valor": 1, "palabra": "perversos-además-garcas"}, {"valor": 1, "palabra": "además-garcas-amenazar"}, {"valor": 1, "palabra": "garcas-amenazar-pueblo"}, {"valor": 1, "palabra": "amenazar-pueblo-llevar"}, {"valor": 1, "palabra": "pueblo-llevar-terror"}, {"valor": 1, "palabra": "llevar-terror-saqueo"}, {"valor": 1, "palabra": "terror-saqueo-pueblo"}, {"valor": 1, "palabra": "saqueo-pueblo-trabajador"}, {"valor": 1, "palabra": "pueblo-trabajador-servicio"}, {"valor": 1, "palabra": "trabajador-servicio-siempre"}, {"valor": 1, "palabra": "servicio-siempre-supermercados"}, {"valor": 1, "palabra": "siempre-supermercados-conseguir"}], "ARG - DANONE - LECHES DE FÓRMULA": [{"valor": 2, "palabra": "yogurt-griego-danone"}, {"valor": 2, "palabra": "griego-danone-profeco"}, {"valor": 1, "palabra": "pañales-huggies-nutrilon"}, {"valor": 1, "palabra": "huggies-nutrilon-cuanto"}, {"valor": 1, "palabra": "nutrilon-cuanto-semanas"}, {"valor": 1, "palabra": "cuanto-semanas-juntar"}, {"valor": 1, "palabra": "semanas-juntar-echarlo"}, {"valor": 1, "palabra": "juntar-echarlo-delirar"}, {"valor": 1, "palabra": "echarlo-delirar-pañales"}, {"valor": 1, "palabra": "delirar-pañales-nutrilon"}, {"valor": 1, "palabra": "pañales-nutrilon-dejalo"}, {"valor": 1, "palabra": "nutrilon-dejalo-siguiendo"}, {"valor": 1, "palabra": "dejalo-siguiendo-sueños"}, {"valor": 1, "palabra": "siguiendo-sueños-yogurt"}, {"valor": 1, "palabra": "sueños-yogurt-griego"}, {"valor": 1, "palabra": "danone-profeco-yogurt"}, {"valor": 1, "palabra": "profeco-yogurt-griego"}], "ARG - DANONE - ETIQUETADO FRONTAL": [{"valor": 1, "palabra": "sanidad-alerta-alérgicos"}, {"valor": 1, "palabra": "alerta-alérgicos-varios"}, {"valor": 1, "palabra": "alérgicos-varios-toblerone"}, {"valor": 1, "palabra": "varios-toblerone-productos"}, {"valor": 1, "palabra": "toblerone-productos-declarados"}, {"valor": 1, "palabra": "productos-declarados-etiquetado"}], "ARG - DANONE - MONITOREO EMERGENTE": []}, "2023-12-13-2023-12-13": {"ARG - DANONE - PROYECTO DE LEY DE REGULACIÓN DE COMERCIALIZACIÓN DE SUCEDÁNEOS DE LECHE MATERNA": [], "ARG - DANONE - LACTEOS Y PRODUCTOS DE ORIGEN VEGETAL \n": [{"valor": 2, "palabra": "calidad-nutricional-presente"}, {"valor": 2, "palabra": "nutricional-presente-meriendas"}, {"valor": 2, "palabra": "presente-meriendas-infantiles"}, {"valor": 1, "palabra": "funcional-apenas-comprarle"}, {"valor": 1, "palabra": "apenas-comprarle-alimentación"}, {"valor": 1, "palabra": "comprarle-alimentación-saludable"}, {"valor": 1, "palabra": "alimentación-saludable-conciencia"}, {"valor": 1, "palabra": "saludable-conciencia-porque"}, {"valor": 1, "palabra": "conciencia-porque-sellos"}, {"valor": 1, "palabra": "porque-sellos-porque"}, {"valor": 1, "palabra": "sellos-porque-alcanzaba"}, {"valor": 1, "palabra": "porque-alcanzaba-ninguno"}, {"valor": 1, "palabra": "alcanzaba-ninguno-calidad"}, {"valor": 1, "palabra": "ninguno-calidad-nutricional"}, {"valor": 1, "palabra": "meriendas-infantiles-calidad"}, {"valor": 1, "palabra": "infantiles-calidad-nutricional"}, {"valor": 1, "palabra": "meriendas-infantiles-través"}], "ARG - DANONE - PRECIOS": [{"valor": 3, "palabra": "industrias-afirman-precio"}, {"valor": 3, "palabra": "afirman-precio-amenaza"}, {"valor": 3, "palabra": "precio-amenaza-futuro"}, {"valor": 3, "palabra": "amenaza-futuro-sector"}, {"valor": 3, "palabra": "futuro-sector-quesero"}, {"valor": 3, "palabra": "sector-quesero-nacional"}, {"valor": 1, "palabra": "acumulada-tambero-especulando"}, {"valor": 1, "palabra": "tambero-especulando-precios"}, {"valor": 1, "palabra": "especulando-precios-neuquén"}, {"valor": 1, "palabra": "precios-neuquén-cuesta"}, {"valor": 1, "palabra": "neuquén-cuesta-mineral"}, {"valor": 1, "palabra": "cuesta-mineral-chocolatada"}, {"valor": 1, "palabra": "mineral-chocolatada-cuesta"}, {"valor": 1, "palabra": "chocolatada-cuesta-distorsión"}, {"valor": 1, "palabra": "cuesta-distorsión-precios"}, {"valor": 1, "palabra": "distorsión-precios-argentina"}, {"valor": 1, "palabra": "precios-argentina-simposio"}, {"valor": 1, "palabra": "argentina-simposio-internacional"}, {"valor": 1, "palabra": "simposio-internacional-psiquiatras"}, {"valor": 1, "palabra": "internacional-psiquiatras-compra"}, {"valor": 1, "palabra": "psiquiatras-compra-podrán"}, {"valor": 1, "palabra": "compra-podrán-aumento"}, {"valor": 1, "palabra": "podrán-aumento-salario"}, {"valor": 1, "palabra": "aumento-salario-mínimo"}, {"valor": 1, "palabra": "salario-mínimo-miserable"}, {"valor": 1, "palabra": "mínimo-miserable-prepararon"}, {"valor": 1, "palabra": "miserable-prepararon-hardvard"}, {"valor": 1, "palabra": "prepararon-hardvard-caputo"}, {"valor": 1, "palabra": "hardvard-caputo-zoncera"}, {"valor": 1, "palabra": "caputo-zoncera-hacerle"}], "ARG - DANONE - LACTEOS Y PRODUCTOS DE ORIGEN VEGETAL - MENCIONES A MARCAS": [{"valor": 3, "palabra": "catador-cindornunca-agarró"}, {"valor": 3, "palabra": "catador-cindorno-agarrar"}, {"valor": 2, "palabra": "cindorno-agarrar-catador"}, {"valor": 2, "palabra": "agarrar-catador-cindornunca"}, {"valor": 2, "palabra": "cindornunca-agarró-catador"}, {"valor": 2, "palabra": "agarró-catador-cindorno"}, {"valor": 2, "palabra": "borrachos-tablón-borrachos"}, {"valor": 2, "palabra": "tablón-borrachos-tablón"}, {"valor": 2, "palabra": "borrachos-tablón-chocolatada"}, {"valor": 2, "palabra": "tablón-chocolatada-cindor"}, {"valor": 2, "palabra": "chocolatada-cindor-galletitas"}, {"valor": 2, "palabra": "cindor-galletitas-pepitos"}, {"valor": 1, "palabra": "compre-serenito-porque"}, {"valor": 1, "palabra": "serenito-porque-andaba"}, {"valor": 1, "palabra": "porque-andaba-antojada"}, {"valor": 1, "palabra": "andaba-antojada-horrible"}, {"valor": 1, "palabra": "antojada-horrible-cuando"}, {"valor": 1, "palabra": "horrible-cuando-riquísimo"}, {"valor": 1, "palabra": "cuando-riquísimo-boicot"}, {"valor": 1, "palabra": "riquísimo-boicot-supermercados"}, {"valor": 1, "palabra": "boicot-supermercados-pajeros"}, {"valor": 1, "palabra": "supermercados-pajeros-fábrica"}, {"valor": 1, "palabra": "pajeros-fábrica-serenísima"}, {"valor": 1, "palabra": "fábrica-serenísima-poroto"}, {"valor": 1, "palabra": "serenísima-poroto-serenisima"}, {"valor": 1, "palabra": "poroto-serenisima-inspirado"}, {"valor": 1, "palabra": "serenisima-inspirado-medios"}, {"valor": 1, "palabra": "inspirado-medios-tibios"}, {"valor": 1, "palabra": "medios-tibios-hermanitos"}, {"valor": 1, "palabra": "tibios-hermanitos-parece"}], "ARG - DANONE - ABASTECIMIENTO EN SUPERMERCADOS": [{"valor": 1, "palabra": "anuncia-faltantes-supermercados"}, {"valor": 1, "palabra": "faltantes-supermercados-gallina"}, {"valor": 1, "palabra": "supermercados-gallina-diciembre"}, {"valor": 1, "palabra": "gallina-diciembre-voluntarios"}, {"valor": 1, "palabra": "diciembre-voluntarios-salesianos"}, {"valor": 1, "palabra": "voluntarios-salesianos-colegios"}, {"valor": 1, "palabra": "salesianos-colegios-puertas"}, {"valor": 1, "palabra": "colegios-puertas-farmacias"}, {"valor": 1, "palabra": "puertas-farmacias-supermercados"}, {"valor": 1, "palabra": "farmacias-supermercados-ciudad"}, {"valor": 1, "palabra": "supermercados-ciudad-recoger"}, {"valor": 1, "palabra": "ciudad-recoger-principalmente"}, {"valor": 1, "palabra": "recoger-principalmente-potitos"}, {"valor": 1, "palabra": "principalmente-potitos-también"}, {"valor": 1, "palabra": "potitos-también-cereales"}, {"valor": 1, "palabra": "también-cereales-papillas"}, {"valor": 1, "palabra": "cereales-papillas-pañales"}, {"valor": 1, "palabra": "papillas-pañales-chupetes"}, {"valor": 1, "palabra": "pañales-chupetes-jajaja"}, {"valor": 1, "palabra": "chupetes-jajaja-perdón"}, {"valor": 1, "palabra": "jajaja-perdón-fiesta"}, {"valor": 1, "palabra": "perdón-fiesta-tragar"}, {"valor": 1, "palabra": "fiesta-tragar-mienten"}, {"valor": 1, "palabra": "tragar-mienten-justificar"}, {"valor": 1, "palabra": "mienten-justificar-ajuste"}, {"valor": 1, "palabra": "justificar-ajuste-saqueo"}], "ARG - DANONE - LECHES DE FÓRMULA": [{"valor": 1, "palabra": "caputo-buscar-encontrar"}, {"valor": 1, "palabra": "buscar-encontrar-precio"}, {"valor": 1, "palabra": "encontrar-precio-nutrilon"}, {"valor": 1, "palabra": "precio-nutrilon-publiquen"}, {"valor": 1, "palabra": "nutrilon-publiquen-nutrilon"}, {"valor": 1, "palabra": "publiquen-nutrilon-aunque"}, {"valor": 1, "palabra": "nutrilon-aunque-ratita"}, {"valor": 1, "palabra": "aunque-ratita-seguiré"}, {"valor": 1, "palabra": "ratita-seguiré-paseandome"}, {"valor": 1, "palabra": "seguiré-paseandome-ferias"}, {"valor": 1, "palabra": "paseandome-ferias-repararé"}, {"valor": 1, "palabra": "ferias-repararé-muchísimo"}, {"valor": 1, "palabra": "repararé-muchísimo-sección"}, {"valor": 1, "palabra": "muchísimo-sección-infantil"}, {"valor": 1, "palabra": "sección-infantil-tiempo"}, {"valor": 1, "palabra": "infantil-tiempo-platicaba"}, {"valor": 1, "palabra": "tiempo-platicaba-gustaban"}, {"valor": 1, "palabra": "platicaba-gustaban-ilustraciones"}, {"valor": 1, "palabra": "gustaban-ilustraciones-libros"}, {"valor": 1, "palabra": "ilustraciones-libros-infantiles"}, {"valor": 1, "palabra": "libros-infantiles-respondió"}, {"valor": 1, "palabra": "infantiles-respondió-quizás"}, {"valor": 1, "palabra": "respondió-quizás-estaba"}, {"valor": 1, "palabra": "quizás-estaba-camino"}, {"valor": 1, "palabra": "estaba-camino-hiciera"}, {"valor": 1, "palabra": "camino-hiciera-verdad"}, {"valor": 1, "palabra": "hiciera-verdad-encanta"}, {"valor": 1, "palabra": "verdad-encanta-literatura"}, {"valor": 1, "palabra": "encanta-literatura-infantil"}, {"valor": 1, "palabra": "literatura-infantil-muchísimos"}], "ARG - DANONE - ETIQUETADO FRONTAL": [], "ARG - DANONE - MONITOREO EMERGENTE": []}, "2023-12-14-2023-12-14": {"ARG - DANONE - PROYECTO DE LEY DE REGULACIÓN DE COMERCIALIZACIÓN DE SUCEDÁNEOS DE LECHE MATERNA": [], "ARG - DANONE - LACTEOS Y PRODUCTOS DE ORIGEN VEGETAL \n": [{"valor": 1, "palabra": "cuidar-necesario-opuesto"}, {"valor": 1, "palabra": "necesario-opuesto-gobierno"}, {"valor": 1, "palabra": "opuesto-gobierno-indica"}, {"valor": 1, "palabra": "gobierno-indica-ingiera"}, {"valor": 1, "palabra": "indica-ingiera-limite"}, {"valor": 1, "palabra": "ingiera-limite-lactosa"}, {"valor": 1, "palabra": "limite-lactosa-griego"}, {"valor": 1, "palabra": "lactosa-griego-limite"}, {"valor": 1, "palabra": "griego-limite-ponele"}, {"valor": 1, "palabra": "limite-ponele-manteca"}, {"valor": 1, "palabra": "ponele-manteca-cocina"}, {"valor": 1, "palabra": "manteca-cocina-manteca"}, {"valor": 1, "palabra": "cocina-manteca-microondas"}, {"valor": 1, "palabra": "manteca-microondas-ingredientes"}, {"valor": 1, "palabra": "microondas-ingredientes-receta"}, {"valor": 1, "palabra": "ingredientes-receta-postre"}, {"valor": 1, "palabra": "receta-postre-fresco"}, {"valor": 1, "palabra": "postre-fresco-original"}, {"valor": 1, "palabra": "fresco-original-sabías"}, {"valor": 1, "palabra": "original-sabías-alimento"}, {"valor": 1, "palabra": "sabías-alimento-fermentado"}, {"valor": 1, "palabra": "alimento-fermentado-valioso"}, {"valor": 1, "palabra": "fermentado-valioso-conclusiones"}, {"valor": 1, "palabra": "valioso-conclusiones-ortega"}, {"valor": 1, "palabra": "conclusiones-ortega-remarcó"}, {"valor": 1, "palabra": "ortega-remarcó-conferencia"}, {"valor": 1, "palabra": "remarcó-conferencia-productos"}, {"valor": 1, "palabra": "conferencia-productos-saludable"}, {"valor": 1, "palabra": "productos-saludable-sostenible"}, {"valor": 1, "palabra": "saludable-sostenible-comerme"}], "ARG - DANONE - PRECIOS": [{"valor": 2, "palabra": "readecuando-precios-sueldos"}, {"valor": 2, "palabra": "precios-sueldos-sueldo"}, {"valor": 2, "palabra": "sueldos-sueldo-ganaba"}, {"valor": 1, "palabra": "piparo-desempleo-aumentos"}, {"valor": 1, "palabra": "desempleo-aumentos-hiperinflación"}, {"valor": 1, "palabra": "aumentos-hiperinflación-ajuste"}, {"valor": 1, "palabra": "hiperinflación-ajuste-negando"}, {"valor": 1, "palabra": "ajuste-negando-derecho"}, {"valor": 1, "palabra": "negando-derecho-circular"}, {"valor": 1, "palabra": "derecho-circular-población"}, {"valor": 1, "palabra": "circular-población-entera"}, {"valor": 1, "palabra": "población-entera-cuando"}, {"valor": 1, "palabra": "entera-cuando-amigos"}, {"valor": 1, "palabra": "cuando-amigos-sojeros"}, {"valor": 1, "palabra": "amigos-sojeros-cortaban"}, {"valor": 1, "palabra": "sojeros-cortaban-derramaban"}, {"valor": 1, "palabra": "cortaban-derramaban-toneladas"}, {"valor": 1, "palabra": "derramaban-toneladas-aplaudias"}, {"valor": 1, "palabra": "toneladas-aplaudias-hipócrita"}, {"valor": 1, "palabra": "aplaudias-hipócrita-roboludo"}, {"valor": 1, "palabra": "hipócrita-roboludo-comprabas"}, {"valor": 1, "palabra": "roboludo-comprabas-bizcochos"}, {"valor": 1, "palabra": "comprabas-bizcochos-sobravaq"}, {"valor": 1, "palabra": "bizcochos-sobravaq-cocahermano"}, {"valor": 1, "palabra": "sobravaq-cocahermano-teniendo"}, {"valor": 1, "palabra": "cocahermano-teniendo-alcanzaigual"}, {"valor": 1, "palabra": "teniendo-alcanzaigual-precio"}, {"valor": 1, "palabra": "alcanzaigual-precio-bizcochos"}, {"valor": 1, "palabra": "precio-bizcochos-comprar"}, {"valor": 1, "palabra": "bizcochos-comprar-docena"}], "ARG - DANONE - LACTEOS Y PRODUCTOS DE ORIGEN VEGETAL - MENCIONES A MARCAS": [{"valor": 2, "palabra": "quiero-cindor-medialunas"}, {"valor": 2, "palabra": "oficina-planta-serenísima"}, {"valor": 1, "palabra": "muchos-frases-primera"}, {"valor": 1, "palabra": "frases-primera-serenitooo"}, {"valor": 1, "palabra": "primera-serenitooo-perdón"}, {"valor": 1, "palabra": "serenitooo-perdón-gustaba"}, {"valor": 1, "palabra": "perdón-gustaba-danonino"}, {"valor": 1, "palabra": "gustaba-danonino-serenito"}, {"valor": 1, "palabra": "danonino-serenito-otario"}, {"valor": 1, "palabra": "serenito-otario-cuesta"}, {"valor": 1, "palabra": "otario-cuesta-comprensión"}, {"valor": 1, "palabra": "cuesta-comprensión-textos"}, {"valor": 1, "palabra": "comprensión-textos-perfil"}, {"valor": 1, "palabra": "textos-perfil-delata"}, {"valor": 1, "palabra": "perfil-delata-cindor"}, {"valor": 1, "palabra": "delata-cindor-hermano"}, {"valor": 1, "palabra": "cindor-hermano-minutos"}, {"valor": 1, "palabra": "hermano-minutos-milanesas"}, {"valor": 1, "palabra": "minutos-milanesas-tomando"}, {"valor": 1, "palabra": "milanesas-tomando-cindor"}, {"valor": 1, "palabra": "tomando-cindor-jsjajajajajajaja"}, {"valor": 1, "palabra": "cindor-jsjajajajajajaja-juntada"}, {"valor": 1, "palabra": "jsjajajajajajaja-juntada-cindor"}, {"valor": 1, "palabra": "juntada-cindor-casancrem"}, {"valor": 1, "palabra": "cindor-casancrem-ustedes"}, {"valor": 1, "palabra": "casancrem-ustedes-tienen"}, {"valor": 1, "palabra": "ustedes-tienen-cindorson"}, {"valor": 1, "palabra": "tienen-cindorson-cagones"}, {"valor": 1, "palabra": "cindorson-cagones-encontré"}, {"valor": 1, "palabra": "cagones-encontré-hombre"}], "ARG - DANONE - ABASTECIMIENTO EN SUPERMERCADOS": [{"valor": 1, "palabra": "presidente-vuelta-supermercados"}, {"valor": 1, "palabra": "vuelta-supermercados-carnicerías"}, {"valor": 1, "palabra": "supermercados-carnicerías-preguntar"}, {"valor": 1, "palabra": "carnicerías-preguntar-cuánto"}, {"valor": 1, "palabra": "preguntar-cuánto-cuesta"}, {"valor": 1, "palabra": "cuánto-cuesta-tanque"}, {"valor": 1, "palabra": "cuesta-tanque-propano"}, {"valor": 1, "palabra": "tanque-propano-conque"}, {"valor": 1, "palabra": "propano-conque-comprar"}, {"valor": 1, "palabra": "conque-comprar-comidas"}, {"valor": 1, "palabra": "comprar-comidas-calidad"}, {"valor": 1, "palabra": "comidas-calidad-tiempo"}, {"valor": 1, "palabra": "calidad-tiempo-tuberculoso"}, {"valor": 1, "palabra": "tiempo-tuberculoso-porque"}, {"valor": 1, "palabra": "tuberculoso-porque-incluso"}, {"valor": 1, "palabra": "porque-incluso-verdad"}, {"valor": 1, "palabra": "incluso-verdad-daniel"}, {"valor": 1, "palabra": "verdad-daniel-completa"}, {"valor": 1, "palabra": "daniel-completa-encontré"}, {"valor": 1, "palabra": "completa-encontré-cualquier"}, {"valor": 1, "palabra": "encontré-cualquier-cantidad"}, {"valor": 1, "palabra": "cualquier-cantidad-extras"}, {"valor": 1, "palabra": "cantidad-extras-supermercados"}, {"valor": 1, "palabra": "extras-supermercados-surtidores"}, {"valor": 1, "palabra": "supermercados-surtidores-repleto"}, {"valor": 1, "palabra": "surtidores-repleto-extras"}, {"valor": 1, "palabra": "repleto-extras-cuando"}, {"valor": 1, "palabra": "extras-cuando-llorando"}, {"valor": 1, "palabra": "cuando-llorando-porque"}, {"valor": 1, "palabra": "llorando-porque-comprar"}], "ARG - DANONE - LECHES DE FÓRMULA": [{"valor": 1, "palabra": "nutrilon-porque-espesa"}, {"valor": 1, "palabra": "porque-espesa-indice"}, {"valor": 1, "palabra": "espesa-indice-nutrilon"}, {"valor": 1, "palabra": "indice-nutrilon-unidad"}, {"valor": 1, "palabra": "nutrilon-unidad-litros"}, {"valor": 1, "palabra": "unidad-litros-nutrilon"}, {"valor": 1, "palabra": "litros-nutrilon-compramos"}, {"valor": 1, "palabra": "nutrilon-compramos-familia"}, {"valor": 1, "palabra": "compramos-familia-decidimos"}, {"valor": 1, "palabra": "familia-decidimos-comprar"}, {"valor": 1, "palabra": "decidimos-comprar-empresas"}, {"valor": 1, "palabra": "comprar-empresas-alimentos"}, {"valor": 1, "palabra": "empresas-alimentos-cuidad"}, {"valor": 1, "palabra": "alimentos-cuidad-hicimos"}, {"valor": 1, "palabra": "cuidad-hicimos-siempre"}, {"valor": 1, "palabra": "hicimos-siempre-caguen"}, {"valor": 1, "palabra": "siempre-caguen-multinacionales"}, {"valor": 1, "palabra": "caguen-multinacionales-chupala"}, {"valor": 1, "palabra": "multinacionales-chupala-chupala"}, {"valor": 1, "palabra": "chupala-chupala-molinos"}, {"valor": 1, "palabra": "chupala-molinos-chupala"}, {"valor": 1, "palabra": "molinos-chupala-danone"}, {"valor": 1, "palabra": "chupala-danone-chupala"}, {"valor": 1, "palabra": "danone-chupala-mastellone"}], "ARG - DANONE - ETIQUETADO FRONTAL": [{"valor": 1, "palabra": "jornada-vacunación-sábado"}, {"valor": 1, "palabra": "vacunación-sábado-diciembre"}, {"valor": 1, "palabra": "sábado-diciembre-puesto"}, {"valor": 1, "palabra": "diciembre-puesto-vacunación"}, {"valor": 1, "palabra": "puesto-vacunación-barrio"}, {"valor": 1, "palabra": "vacunación-barrio-altagracia"}, {"valor": 1, "palabra": "barrio-altagracia-managua"}, {"valor": 1, "palabra": "altagracia-managua-colegio"}, {"valor": 1, "palabra": "managua-colegio-emmanuel"}, {"valor": 1, "palabra": "colegio-emmanuel-mongalo"}, {"valor": 1, "palabra": "emmanuel-mongalo-semáforo"}, {"valor": 1, "palabra": "mongalo-semáforo-presencia"}, {"valor": 1, "palabra": "semáforo-presencia-almendra"}, {"valor": 1, "palabra": "presencia-almendra-chocolate"}, {"valor": 1, "palabra": "almendra-chocolate-nougat"}, {"valor": 1, "palabra": "chocolate-nougat-almendras"}, {"valor": 1, "palabra": "nougat-almendras-declaradas"}, {"valor": 1, "palabra": "almendras-declaradas-etiquetado"}, {"valor": 1, "palabra": "declaradas-etiquetado-español"}, {"valor": 1, "palabra": "etiquetado-español-toblerone"}, {"valor": 1, "palabra": "español-toblerone-procedente"}, {"valor": 1, "palabra": "toblerone-procedente-información"}, {"valor": 1, "palabra": "procedente-información-ninguna"}, {"valor": 1, "palabra": "información-ninguna-fórmula"}, {"valor": 1, "palabra": "ninguna-fórmula-láctea"}, {"valor": 1, "palabra": "fórmula-láctea-infantil"}, {"valor": 1, "palabra": "láctea-infantil-cumple"}, {"valor": 1, "palabra": "infantil-cumple-normativas"}, {"valor": 1, "palabra": "cumple-normativas-etiquetado"}, {"valor": 1, "palabra": "normativas-etiquetado-principales"}], "ARG - DANONE - MONITOREO EMERGENTE": []}, "2023-12-15-2023-12-15": {"ARG - DANONE - PROYECTO DE LEY DE REGULACIÓN DE COMERCIALIZACIÓN DE SUCEDÁNEOS DE LECHE MATERNA": [], "ARG - DANONE - LACTEOS Y PRODUCTOS DE ORIGEN VEGETAL \n": [{"valor": 1, "palabra": "ciertamente-textura-mayoría"}, {"valor": 1, "palabra": "textura-mayoría-griegos"}, {"valor": 1, "palabra": "mayoría-griegos-endulzarlo"}, {"valor": 1, "palabra": "griegos-endulzarlo-edulcorante"}, {"valor": 1, "palabra": "endulzarlo-edulcorante-disfrutable"}, {"valor": 1, "palabra": "edulcorante-disfrutable-bastante"}, {"valor": 1, "palabra": "disfrutable-bastante-nutritivo"}, {"valor": 1, "palabra": "bastante-nutritivo-también"}, {"valor": 1, "palabra": "nutritivo-también-nueces"}, {"valor": 1, "palabra": "también-nueces-bendición"}, {"valor": 1, "palabra": "nueces-bendición-lactolanda"}, {"valor": 1, "palabra": "bendición-lactolanda-excelencia"}, {"valor": 1, "palabra": "lactolanda-excelencia-bosnia"}, {"valor": 1, "palabra": "excelencia-bosnia-serbia"}, {"valor": 1, "palabra": "bosnia-serbia-partes"}, {"valor": 1, "palabra": "serbia-partes-balcanes"}, {"valor": 1, "palabra": "partes-balcanes-especie"}, {"valor": 1, "palabra": "balcanes-especie-empanada"}, {"valor": 1, "palabra": "especie-empanada-pescado"}, {"valor": 1, "palabra": "empanada-pescado-generalmente"}, {"valor": 1, "palabra": "pescado-generalmente-ingredientes"}, {"valor": 1, "palabra": "generalmente-ingredientes-servir"}, {"valor": 1, "palabra": "ingredientes-servir-acompañado"}, {"valor": 1, "palabra": "servir-acompañado-beneficios"}, {"valor": 1, "palabra": "acompañado-beneficios-nuestra"}], "ARG - DANONE - PRECIOS": [{"valor": 3, "palabra": "aprovecha-precio-cafetera"}, {"valor": 3, "palabra": "precio-cafetera-cecotec"}, {"valor": 3, "palabra": "cafetera-cecotec-bianca"}, {"valor": 3, "palabra": "cecotec-bianca-depósito"}, {"valor": 3, "palabra": "bianca-depósito-costaba"}, {"valor": 2, "palabra": "aumenta-aumenta-aumenta"}, {"valor": 2, "palabra": "nicaragua-compares-precios"}, {"valor": 2, "palabra": "compares-precios-gasolina"}, {"valor": 2, "palabra": "precios-gasolina-energía"}, {"valor": 2, "palabra": "gasolina-energía-subsidio"}, {"valor": 2, "palabra": "energía-subsidio-factura"}, {"valor": 2, "palabra": "subsidio-factura-protesta"}, {"valor": 2, "palabra": "factura-protesta-chipote"}, {"valor": 2, "palabra": "protesta-chipote-límite"}, {"valor": 2, "palabra": "chipote-límite-tiempo"}, {"valor": 2, "palabra": "límite-tiempo-juicio"}, {"valor": 2, "palabra": "tiempo-juicio-destierro"}, {"valor": 2, "palabra": "depósito-costaba-aprovecha"}, {"valor": 2, "palabra": "costaba-aprovecha-precio"}, {"valor": 2, "palabra": "precio-promedio-puerta"}, {"valor": 2, "palabra": "promedio-puerta-corral"}, {"valor": 2, "palabra": "puerta-corral-reporte"}, {"valor": 2, "palabra": "corral-reporte-detallado"}, {"valor": 2, "palabra": "reporte-detallado-estado"}, {"valor": 2, "palabra": "detallado-estado-fuente"}, {"valor": 2, "palabra": "estado-fuente-instituto"}, {"valor": 2, "palabra": "fuente-instituto-venezolano"}, {"valor": 2, "palabra": "instituto-venezolano-invelecar"}, {"valor": 2, "palabra": "venezolano-invelecar-boletín"}, {"valor": 2, "palabra": "invelecar-boletín-número"}], "ARG - DANONE - LACTEOS Y PRODUCTOS DE ORIGEN VEGETAL - MENCIONES A MARCAS": [{"valor": 2, "palabra": "pasando-dirigible-serenísima"}, {"valor": 1, "palabra": "awwwwww-dijiste-privado"}, {"valor": 1, "palabra": "dijiste-privado-también"}, {"valor": 1, "palabra": "privado-también-gordiiii"}, {"valor": 1, "palabra": "también-gordiiii-pelotudo"}, {"valor": 1, "palabra": "gordiiii-pelotudo-también"}, {"valor": 1, "palabra": "pelotudo-también-seguro"}, {"valor": 1, "palabra": "también-seguro-cindor"}, {"valor": 1, "palabra": "seguro-cindor-virgen"}, {"valor": 1, "palabra": "cindor-virgen-perdón"}, {"valor": 1, "palabra": "virgen-perdón-entiendo"}, {"valor": 1, "palabra": "perdón-entiendo-cuando"}, {"valor": 1, "palabra": "entiendo-cuando-chamuyan"}, {"valor": 1, "palabra": "cuando-chamuyan-hombre"}, {"valor": 1, "palabra": "chamuyan-hombre-extraño"}, {"valor": 1, "palabra": "hombre-extraño-serenísima"}, {"valor": 1, "palabra": "extraño-serenísima-quiénes"}, {"valor": 1, "palabra": "serenísima-quiénes-dijieron"}, {"valor": 1, "palabra": "quiénes-dijieron-chiriquí"}, {"valor": 1, "palabra": "dijieron-chiriquí-cuando"}, {"valor": 1, "palabra": "chiriquí-cuando-enteré"}, {"valor": 1, "palabra": "cuando-enteré-esocomo"}, {"valor": 1, "palabra": "enteré-esocomo-jajaja"}, {"valor": 1, "palabra": "esocomo-jajaja-cindor"}, {"valor": 1, "palabra": "jajaja-cindor-hinchada"}, {"valor": 1, "palabra": "cindor-hinchada-pincha"}, {"valor": 1, "palabra": "hinchada-pincha-muerto"}, {"valor": 1, "palabra": "pincha-muerto-discord"}, {"valor": 1, "palabra": "muerto-discord-deporte"}, {"valor": 1, "palabra": "discord-deporte-reconocen"}], "ARG - DANONE - ABASTECIMIENTO EN SUPERMERCADOS": [{"valor": 1, "palabra": "maslechon-cumple-trabajo"}, {"valor": 1, "palabra": "cumple-trabajo-mercenario"}, {"valor": 1, "palabra": "trabajo-mercenario-pelado"}, {"valor": 1, "palabra": "mercenario-pelado-resentido"}, {"valor": 1, "palabra": "pelado-resentido-purista"}, {"valor": 1, "palabra": "resentido-purista-pesimista"}, {"valor": 1, "palabra": "purista-pesimista-anarcocapitalista"}, {"valor": 1, "palabra": "pesimista-anarcocapitalista-amistad"}, {"valor": 1, "palabra": "anarcocapitalista-amistad-códigos"}, {"valor": 1, "palabra": "amistad-códigos-cuenta"}, {"valor": 1, "palabra": "códigos-cuenta-ambientalismo"}, {"valor": 1, "palabra": "cuenta-ambientalismo-político"}, {"valor": 1, "palabra": "ambientalismo-político-cuando"}, {"valor": 1, "palabra": "político-cuando-plantar"}, {"valor": 1, "palabra": "cuando-plantar-arboles"}, {"valor": 1, "palabra": "plantar-arboles-derramando"}, {"valor": 1, "palabra": "arboles-derramando-supermercados"}, {"valor": 1, "palabra": "derramando-supermercados-pegándose"}, {"valor": 1, "palabra": "supermercados-pegándose-nevada"}, {"valor": 1, "palabra": "pegándose-nevada-barata"}, {"valor": 1, "palabra": "nevada-barata-supermercados"}, {"valor": 1, "palabra": "barata-supermercados-ejemplo"}, {"valor": 1, "palabra": "supermercados-ejemplo-primero"}, {"valor": 1, "palabra": "ejemplo-primero-hungría"}, {"valor": 1, "palabra": "primero-hungría-reventó"}, {"valor": 1, "palabra": "hungría-reventó-cadena"}, {"valor": 1, "palabra": "reventó-cadena-suministros"}, {"valor": 1, "palabra": "cadena-suministros-supermercados"}, {"valor": 1, "palabra": "suministros-supermercados-compatriotas"}, {"valor": 1, "palabra": "supermercados-compatriotas-organizaban"}], "ARG - DANONE - LECHES DE FÓRMULA": [{"valor": 1, "palabra": "nutrilon-vendría-alguna"}, {"valor": 1, "palabra": "vendría-alguna-persona"}, {"valor": 1, "palabra": "alguna-persona-necesite"}, {"valor": 1, "palabra": "persona-necesite-nutrilón"}, {"valor": 1, "palabra": "necesite-nutrilón-avisan"}, {"valor": 1, "palabra": "nutrilón-avisan-gracias"}], "ARG - DANONE - ETIQUETADO FRONTAL": [{"valor": 1, "palabra": "porque-penales-juegan"}, {"valor": 1, "palabra": "penales-juegan-octogonos"}], "ARG - DANONE - MONITOREO EMERGENTE": []}, "2023-12-16-2023-12-16": {"ARG - DANONE - PROYECTO DE LEY DE REGULACIÓN DE COMERCIALIZACIÓN DE SUCEDÁNEOS DE LECHE MATERNA": [], "ARG - DANONE - LACTEOS Y PRODUCTOS DE ORIGEN VEGETAL \n": [{"valor": 1, "palabra": "quadratín-aunque-mexicanos"}, {"valor": 1, "palabra": "aunque-mexicanos-incluimos"}, {"valor": 1, "palabra": "mexicanos-incluimos-griego"}, {"valor": 1, "palabra": "incluimos-griego-desayuno"}, {"valor": 1, "palabra": "griego-desayuno-profeco"}, {"valor": 1, "palabra": "desayuno-profeco-alertó"}, {"valor": 1, "palabra": "profeco-alertó-algunas"}, {"valor": 1, "palabra": "alertó-algunas-marcas"}, {"valor": 1, "palabra": "algunas-marcas-contenido"}, {"valor": 1, "palabra": "marcas-contenido-azúcares"}, {"valor": 1, "palabra": "contenido-azúcares-edulcorantes"}, {"valor": 1, "palabra": "azúcares-edulcorantes-ingredientes"}, {"valor": 1, "palabra": "edulcorantes-ingredientes-información"}, {"valor": 1, "palabra": "ingredientes-información-griego"}, {"valor": 1, "palabra": "información-griego-tomado"}, {"valor": 1, "palabra": "griego-tomado-popularidad"}, {"valor": 1, "palabra": "tomado-popularidad-contenido"}, {"valor": 1, "palabra": "popularidad-contenido-proteína"}, {"valor": 1, "palabra": "contenido-proteína-embargo"}, {"valor": 1, "palabra": "proteína-embargo-muchos"}, {"valor": 1, "palabra": "embargo-muchos-productos"}, {"valor": 1, "palabra": "muchos-productos-contienen"}, {"valor": 1, "palabra": "productos-contienen-también"}, {"valor": 1, "palabra": "contienen-también-azúcares"}, {"valor": 1, "palabra": "también-azúcares-calorías"}, {"valor": 1, "palabra": "azúcares-calorías-exceso"}, {"valor": 1, "palabra": "calorías-exceso-afectar"}, {"valor": 1, "palabra": "exceso-afectar-consulta"}, {"valor": 1, "palabra": "afectar-consulta-información"}], "ARG - DANONE - PRECIOS": [{"valor": 1, "palabra": "aumenten-salario-huelga"}, {"valor": 1, "palabra": "salario-huelga-precios"}, {"valor": 1, "palabra": "huelga-precios-huevos"}, {"valor": 1, "palabra": "precios-huevos-mediana"}, {"valor": 1, "palabra": "huevos-mediana-alguien"}, {"valor": 1, "palabra": "mediana-alguien-oferta"}, {"valor": 1, "palabra": "alguien-oferta-demanda"}, {"valor": 1, "palabra": "oferta-demanda-inflación"}, {"valor": 1, "palabra": "demanda-inflación-quiere"}, {"valor": 1, "palabra": "inflación-quiere-simples"}, {"valor": 1, "palabra": "quiere-simples-palabras"}, {"valor": 1, "palabra": "simples-palabras-revierte"}, {"valor": 1, "palabra": "palabras-revierte-costará"}, {"valor": 1, "palabra": "revierte-costará-escuché"}, {"valor": 1, "palabra": "costará-escuché-periodista"}, {"valor": 1, "palabra": "escuché-periodista-random"}, {"valor": 1, "palabra": "periodista-random-precio"}, {"valor": 1, "palabra": "random-precio-costaría"}, {"valor": 1, "palabra": "precio-costaría-lácteo"}, {"valor": 1, "palabra": "costaría-lácteo-seguro"}, {"valor": 1, "palabra": "lácteo-seguro-hojaldre"}, {"valor": 1, "palabra": "seguro-hojaldre-consiguen"}, {"valor": 1, "palabra": "hojaldre-consiguen-tremendos"}, {"valor": 1, "palabra": "consiguen-tremendos-precios"}, {"valor": 1, "palabra": "tremendos-precios-estúpida"}, {"valor": 1, "palabra": "precios-estúpida-comerciantes"}, {"valor": 1, "palabra": "estúpida-comerciantes-argentina"}, {"valor": 1, "palabra": "comerciantes-argentina-lechemanteca"}, {"valor": 1, "palabra": "argentina-lechemanteca-yogurt"}, {"valor": 1, "palabra": "lechemanteca-yogurt-cobran"}], "ARG - DANONE - LACTEOS Y PRODUCTOS DE ORIGEN VEGETAL - MENCIONES A MARCAS": [{"valor": 3, "palabra": "bigotin-cindor-empobrecido"}, {"valor": 1, "palabra": "cuenta-ganaron-corners"}, {"valor": 1, "palabra": "ganaron-corners-cuando"}, {"valor": 1, "palabra": "corners-cuando-políticos"}, {"valor": 1, "palabra": "cuando-políticos-encarguen"}, {"valor": 1, "palabra": "políticos-encarguen-tiendas"}, {"valor": 1, "palabra": "encarguen-tiendas-podria"}, {"valor": 1, "palabra": "tiendas-podria-serenisima"}, {"valor": 1, "palabra": "podria-serenisima-lactosa"}, {"valor": 1, "palabra": "serenisima-lactosa-tambien"}, {"valor": 1, "palabra": "lactosa-tambien-condensada"}, {"valor": 1, "palabra": "tambien-condensada-nestle"}, {"valor": 1, "palabra": "condensada-nestle-lactosa"}, {"valor": 1, "palabra": "nestle-lactosa-aunque"}, {"valor": 1, "palabra": "lactosa-aunque-tambien"}, {"valor": 1, "palabra": "aunque-tambien-recetas"}, {"valor": 1, "palabra": "tambien-recetas-caseras"}, {"valor": 1, "palabra": "recetas-caseras-condensada"}, {"valor": 1, "palabra": "caseras-condensada-lactosa"}, {"valor": 1, "palabra": "condensada-lactosa-dejarle"}, {"valor": 1, "palabra": "lactosa-dejarle-estaba"}, {"valor": 1, "palabra": "dejarle-estaba-acuerdo"}, {"valor": 1, "palabra": "estaba-acuerdo-procedía"}, {"valor": 1, "palabra": "acuerdo-procedía-hacerle"}, {"valor": 1, "palabra": "procedía-hacerle-simplemente"}, {"valor": 1, "palabra": "hacerle-simplemente-cortar"}, {"valor": 1, "palabra": "simplemente-cortar-relación"}, {"valor": 1, "palabra": "cortar-relación-estaban"}, {"valor": 1, "palabra": "relación-estaban-proceso"}, {"valor": 1, "palabra": "estaban-proceso-concretar"}], "ARG - DANONE - ABASTECIMIENTO EN SUPERMERCADOS": [{"valor": 1, "palabra": "entender-amistad-hombre"}, {"valor": 1, "palabra": "amistad-hombre-camion"}, {"valor": 1, "palabra": "hombre-camion-lionel"}, {"valor": 1, "palabra": "camion-lionel-andrés"}, {"valor": 1, "palabra": "lionel-andrés-cortar"}, {"valor": 1, "palabra": "andrés-cortar-amistad"}, {"valor": 1, "palabra": "cortar-amistad-evasor"}, {"valor": 1, "palabra": "amistad-evasor-impuestos"}, {"valor": 1, "palabra": "evasor-impuestos-guarden"}, {"valor": 1, "palabra": "impuestos-guarden-negroo"}, {"valor": 1, "palabra": "guarden-negroo-intolerante"}, {"valor": 1, "palabra": "negroo-intolerante-lactosa"}, {"valor": 1, "palabra": "intolerante-lactosa-negroo"}, {"valor": 1, "palabra": "lactosa-negroo-recuerdes"}, {"valor": 1, "palabra": "negroo-recuerdes-negroo"}, {"valor": 1, "palabra": "recuerdes-negroo-automáticamente"}, {"valor": 1, "palabra": "negroo-automáticamente-cuando"}, {"valor": 1, "palabra": "automáticamente-cuando-amistad"}, {"valor": 1, "palabra": "cuando-amistad-comparación"}, {"valor": 1, "palabra": "amistad-comparación-estúpida"}, {"valor": 1, "palabra": "comparación-estúpida-ningún"}, {"valor": 1, "palabra": "estúpida-ningún-bajado"}, {"valor": 1, "palabra": "ningún-bajado-tenderos"}, {"valor": 1, "palabra": "bajado-tenderos-supermercados"}, {"valor": 1, "palabra": "tenderos-supermercados-grandes"}, {"valor": 1, "palabra": "supermercados-grandes-promociones"}, {"valor": 1, "palabra": "grandes-promociones-pequeños"}, {"valor": 1, "palabra": "promociones-pequeños-tenderos"}, {"valor": 1, "palabra": "pequeños-tenderos-pueden"}, {"valor": 1, "palabra": "tenderos-pueden-ofertas"}], "ARG - DANONE - LECHES DE FÓRMULA": [{"valor": 1, "palabra": "nutrilon-jajajajajaja-preguntame"}, {"valor": 1, "palabra": "jajajajajaja-preguntame-barato"}], "ARG - DANONE - ETIQUETADO FRONTAL": [], "ARG - DANONE - MONITOREO EMERGENTE": []}, "2023-12-17-2023-12-17": {"ARG - DANONE - PROYECTO DE LEY DE REGULACIÓN DE COMERCIALIZACIÓN DE SUCEDÁNEOS DE LECHE MATERNA": [], "ARG - DANONE - LACTEOS Y PRODUCTOS DE ORIGEN VEGETAL \n": [{"valor": 1, "palabra": "airfryer-importó-siguientes"}, {"valor": 1, "palabra": "importó-siguientes-ingredientes"}, {"valor": 1, "palabra": "siguientes-ingredientes-sartén"}, {"valor": 1, "palabra": "ingredientes-sartén-espectacularidad"}, {"valor": 1, "palabra": "sartén-espectacularidad-anoten"}, {"valor": 1, "palabra": "espectacularidad-anoten-bananos"}, {"valor": 1, "palabra": "anoten-bananos-lástima"}, {"valor": 1, "palabra": "bananos-lástima-huevos"}, {"valor": 1, "palabra": "lástima-huevos-hojuelas"}, {"valor": 1, "palabra": "huevos-hojuelas-griego"}, {"valor": 1, "palabra": "hojuelas-griego-poquito"}, {"valor": 1, "palabra": "griego-poquito-mantequilla"}, {"valor": 1, "palabra": "poquito-mantequilla-azúcar"}, {"valor": 1, "palabra": "mantequilla-azúcar-subestimado"}, {"valor": 1, "palabra": "azúcar-subestimado-perder"}, {"valor": 1, "palabra": "subestimado-perder-snacks"}, {"valor": 1, "palabra": "perder-snacks-saludables"}, {"valor": 1, "palabra": "snacks-saludables-ejemplo"}, {"valor": 1, "palabra": "saludables-ejemplo-frutas"}, {"valor": 1, "palabra": "ejemplo-frutas-verduras"}, {"valor": 1, "palabra": "frutas-verduras-griego"}, {"valor": 1, "palabra": "verduras-griego-frutos"}, {"valor": 1, "palabra": "griego-frutos-semillas"}, {"valor": 1, "palabra": "frutos-semillas-moderación"}, {"valor": 1, "palabra": "semillas-moderación-snacks"}, {"valor": 1, "palabra": "moderación-snacks-tienen"}, {"valor": 1, "palabra": "snacks-tienen-saludables"}, {"valor": 1, "palabra": "tienen-saludables-jajaja"}, {"valor": 1, "palabra": "saludables-jajaja-felicidades"}, {"valor": 1, "palabra": "jajaja-felicidades-jovencito"}], "ARG - DANONE - PRECIOS": [{"valor": 4, "palabra": "aumentó-aumentó-eliminación"}, {"valor": 4, "palabra": "aumentó-eliminación-subsidios"}, {"valor": 4, "palabra": "eliminación-subsidios-transporte"}, {"valor": 4, "palabra": "subsidios-transporte-eliminación"}, {"valor": 4, "palabra": "transporte-eliminación-devolución"}, {"valor": 4, "palabra": "eliminación-devolución-devaluación"}, {"valor": 4, "palabra": "devolución-devaluación-oficial"}, {"valor": 3, "palabra": "gobierno-aumentó-aumentó"}, {"valor": 2, "palabra": "precio-máximo-hojaldre"}, {"valor": 1, "palabra": "explicación-precio-huevos"}, {"valor": 1, "palabra": "precio-huevos-madagascar"}, {"valor": 1, "palabra": "huevos-madagascar-barrica"}, {"valor": 1, "palabra": "madagascar-barrica-venezolano"}, {"valor": 1, "palabra": "barrica-venezolano-apeninos"}, {"valor": 1, "palabra": "venezolano-apeninos-italia"}, {"valor": 1, "palabra": "apeninos-italia-secreto"}, {"valor": 1, "palabra": "italia-secreto-eliodoro"}, {"valor": 1, "palabra": "secreto-eliodoro-inflación"}, {"valor": 1, "palabra": "eliodoro-inflación-compuesta"}, {"valor": 1, "palabra": "inflación-compuesta-aproximadamente"}, {"valor": 1, "palabra": "compuesta-aproximadamente-verifícalo"}, {"valor": 1, "palabra": "aproximadamente-verifícalo-fácilmente"}, {"valor": 1, "palabra": "verifícalo-fácilmente-teniendo"}, {"valor": 1, "palabra": "fácilmente-teniendo-cuenta"}, {"valor": 1, "palabra": "teniendo-cuenta-estaba"}, {"valor": 1, "palabra": "cuenta-estaba-aumento"}, {"valor": 1, "palabra": "estaba-aumento-abrazo"}, {"valor": 1, "palabra": "aumento-abrazo-grande"}, {"valor": 1, "palabra": "abrazo-grande-impresionante"}, {"valor": 1, "palabra": "grande-impresionante-asientos"}], "ARG - DANONE - LACTEOS Y PRODUCTOS DE ORIGEN VEGETAL - MENCIONES A MARCAS": [{"valor": 4, "palabra": "gracias-gracias-gracias"}, {"valor": 2, "palabra": "cindor-protein-serenisima"}, {"valor": 2, "palabra": "méxico-conocer-walmart"}, {"valor": 2, "palabra": "méxico-temprano-compras"}, {"valor": 2, "palabra": "temprano-compras-walmart"}, {"valor": 2, "palabra": "compras-walmart-naranja"}, {"valor": 2, "palabra": "walmart-naranja-pateéy"}, {"valor": 2, "palabra": "naranja-pateéy-titular"}, {"valor": 2, "palabra": "pateéy-titular-indiscutido"}, {"valor": 2, "palabra": "titular-indiscutido-aztecas"}, {"valor": 2, "palabra": "indiscutido-aztecas-méxico"}, {"valor": 2, "palabra": "aztecas-méxico-sueldo"}, {"valor": 2, "palabra": "méxico-sueldo-dieron"}, {"valor": 2, "palabra": "sueldo-dieron-selección"}, {"valor": 1, "palabra": "gracias-gracias-surgió"}, {"valor": 1, "palabra": "gracias-surgió-necesidad"}, {"valor": 1, "palabra": "surgió-necesidad-inmensa"}, {"valor": 1, "palabra": "necesidad-inmensa-aprender"}, {"valor": 1, "palabra": "inmensa-aprender-batería"}, {"valor": 1, "palabra": "aprender-batería-gracias"}, {"valor": 1, "palabra": "batería-gracias-gracias"}, {"valor": 1, "palabra": "gracias-gracias-cordobés"}, {"valor": 1, "palabra": "gracias-cordobés-durante"}, {"valor": 1, "palabra": "cordobés-durante-temporal"}, {"valor": 1, "palabra": "durante-temporal-protejan"}, {"valor": 1, "palabra": "temporal-protejan-manzana"}, {"valor": 1, "palabra": "protejan-manzana-cindor"}, {"valor": 1, "palabra": "manzana-cindor-chetos"}, {"valor": 1, "palabra": "cindor-chetos-pueblo"}, {"valor": 1, "palabra": "chetos-pueblo-cindor"}], "ARG - DANONE - ABASTECIMIENTO EN SUPERMERCADOS": [{"valor": 1, "palabra": "amistad-hermano-poción"}, {"valor": 1, "palabra": "hermano-poción-amistad"}, {"valor": 1, "palabra": "poción-amistad-tortilla"}, {"valor": 1, "palabra": "amistad-tortilla-venden"}, {"valor": 1, "palabra": "tortilla-venden-supermercados"}, {"valor": 1, "palabra": "venden-supermercados-caraotas"}, {"valor": 1, "palabra": "supermercados-caraotas-negras"}, {"valor": 1, "palabra": "caraotas-negras-molidas"}, {"valor": 1, "palabra": "negras-molidas-añadir"}, {"valor": 1, "palabra": "molidas-añadir-molida"}, {"valor": 1, "palabra": "añadir-molida-guisado"}, {"valor": 1, "palabra": "molida-guisado-lechuga"}, {"valor": 1, "palabra": "guisado-lechuga-tomate"}, {"valor": 1, "palabra": "lechuga-tomate-cebolla"}, {"valor": 1, "palabra": "tomate-cebolla-guacamole"}, {"valor": 1, "palabra": "cebolla-guacamole-rallado"}, {"valor": 1, "palabra": "guacamole-rallado-tostadas"}, {"valor": 1, "palabra": "rallado-tostadas-familia"}, {"valor": 1, "palabra": "tostadas-familia-cuánto"}, {"valor": 1, "palabra": "familia-cuánto-cuesta"}, {"valor": 1, "palabra": "cuánto-cuesta-presidente"}, {"valor": 1, "palabra": "cuesta-presidente-boleto"}, {"valor": 1, "palabra": "presidente-boleto-insumos"}, {"valor": 1, "palabra": "boleto-insumos-aumentaron"}, {"valor": 1, "palabra": "insumos-aumentaron-conque"}, {"valor": 1, "palabra": "aumentaron-conque-saqueando"}, {"valor": 1, "palabra": "conque-saqueando-bolsillo"}, {"valor": 1, "palabra": "saqueando-bolsillo-amigos"}, {"valor": 1, "palabra": "bolsillo-amigos-amistad"}, {"valor": 1, "palabra": "amigos-amistad-lealtadera"}], "ARG - DANONE - LECHES DE FÓRMULA": [], "ARG - DANONE - ETIQUETADO FRONTAL": [], "ARG - DANONE - MONITOREO EMERGENTE": []}, "2023-12-18-2023-12-18": {"ARG - DANONE - PROYECTO DE LEY DE REGULACIÓN DE COMERCIALIZACIÓN DE SUCEDÁNEOS DE LECHE MATERNA": [], "ARG - DANONE - LACTEOS Y PRODUCTOS DE ORIGEN VEGETAL \n": [{"valor": 1, "palabra": "recomienda-alimento-benéfico"}, {"valor": 1, "palabra": "alimento-benéfico-digestiva"}, {"valor": 1, "palabra": "benéfico-digestiva-prueba"}, {"valor": 1, "palabra": "digestiva-prueba-conocimientos"}, {"valor": 1, "palabra": "prueba-conocimientos-puedes"}, {"valor": 1, "palabra": "conocimientos-puedes-consultar"}, {"valor": 1, "palabra": "puedes-consultar-nuestro"}, {"valor": 1, "palabra": "consultar-nuestro-artículo"}, {"valor": 1, "palabra": "nuestro-artículo-beneficios"}, {"valor": 1, "palabra": "artículo-beneficios-disgestión"}, {"valor": 1, "palabra": "beneficios-disgestión-consumo"}, {"valor": 1, "palabra": "disgestión-consumo-consejos"}, {"valor": 1, "palabra": "consumo-consejos-alarga"}, {"valor": 1, "palabra": "consejos-alarga-mandamientos"}, {"valor": 1, "palabra": "alarga-mandamientos-harvard"}], "ARG - DANONE - PRECIOS": [{"valor": 1, "palabra": "cantidad-podría-millones"}, {"valor": 1, "palabra": "podría-millones-gobierno"}, {"valor": 1, "palabra": "millones-gobierno-suspendió"}, {"valor": 1, "palabra": "gobierno-suspendió-congreso"}, {"valor": 1, "palabra": "suspendió-congreso-diputados"}, {"valor": 1, "palabra": "congreso-diputados-suponer"}, {"valor": 1, "palabra": "diputados-suponer-aumento"}, {"valor": 1, "palabra": "suponer-aumento-constata"}, {"valor": 1, "palabra": "aumento-constata-aumento"}, {"valor": 1, "palabra": "constata-aumento-mortalidad"}, {"valor": 1, "palabra": "aumento-mortalidad-contratos"}, {"valor": 1, "palabra": "mortalidad-contratos-indefinidos"}, {"valor": 1, "palabra": "contratos-indefinidos-reforma"}, {"valor": 1, "palabra": "indefinidos-reforma-laboral"}, {"valor": 1, "palabra": "reforma-laboral-esgueva"}, {"valor": 1, "palabra": "laboral-esgueva-madurado"}, {"valor": 1, "palabra": "esgueva-madurado-corteza"}, {"valor": 1, "palabra": "madurado-corteza-natural"}, {"valor": 1, "palabra": "corteza-natural-aproximado"}, {"valor": 1, "palabra": "natural-aproximado-elaborado"}, {"valor": 1, "palabra": "aproximado-elaborado-precio"}, {"valor": 1, "palabra": "elaborado-precio-oferta"}, {"valor": 1, "palabra": "precio-oferta-mencionó"}, {"valor": 1, "palabra": "oferta-mencionó-subcampeón"}, {"valor": 1, "palabra": "mencionó-subcampeón-siempre"}, {"valor": 1, "palabra": "subcampeón-siempre-prensa"}, {"valor": 1, "palabra": "siempre-prensa-amarillista"}, {"valor": 1, "palabra": "prensa-amarillista-precio"}, {"valor": 1, "palabra": "amarillista-precio-tercer"}, {"valor": 1, "palabra": "precio-tercer-grande"}], "ARG - DANONE - LACTEOS Y PRODUCTOS DE ORIGEN VEGETAL - MENCIONES A MARCAS": [{"valor": 6, "palabra": "gracias-gracias-gracias"}, {"valor": 1, "palabra": "regianito-serenisima-adelante"}, {"valor": 1, "palabra": "serenisima-adelante-naxhito"}, {"valor": 1, "palabra": "adelante-naxhito-inverti"}, {"valor": 1, "palabra": "naxhito-inverti-rancio"}, {"valor": 1, "palabra": "inverti-rancio-serenito"}, {"valor": 1, "palabra": "rancio-serenito-meneja"}, {"valor": 1, "palabra": "serenito-meneja-yogurisimo"}, {"valor": 1, "palabra": "meneja-yogurisimo-jugaban"}, {"valor": 1, "palabra": "yogurisimo-jugaban-mejores"}, {"valor": 1, "palabra": "jugaban-mejores-torneos"}, {"valor": 1, "palabra": "mejores-torneos-plazas"}, {"valor": 1, "palabra": "torneos-plazas-juegan"}, {"valor": 1, "palabra": "plazas-juegan-talleres"}, {"valor": 1, "palabra": "juegan-talleres-amigoque"}, {"valor": 1, "palabra": "talleres-amigoque-riquelme"}, {"valor": 1, "palabra": "amigoque-riquelme-eternidad"}, {"valor": 1, "palabra": "riquelme-eternidad-ganamos"}, {"valor": 1, "palabra": "eternidad-ganamos-cindora"}, {"valor": 1, "palabra": "ganamos-cindora-gestión"}, {"valor": 1, "palabra": "cindora-gestión-rajaron"}, {"valor": 1, "palabra": "gestión-rajaron-perder"}, {"valor": 1, "palabra": "rajaron-perder-decadas"}, {"valor": 1, "palabra": "perder-decadas-excelsa"}, {"valor": 1, "palabra": "decadas-excelsa-magnanimidad"}, {"valor": 1, "palabra": "excelsa-magnanimidad-alteza"}, {"valor": 1, "palabra": "magnanimidad-alteza-serenísima"}, {"valor": 1, "palabra": "alteza-serenísima-portador"}, {"valor": 1, "palabra": "serenísima-portador-adalid"}, {"valor": 1, "palabra": "portador-adalid-derechos"}], "ARG - DANONE - ABASTECIMIENTO EN SUPERMERCADOS": [{"valor": 1, "palabra": "pasado-olímpicamente-saqueo"}, {"valor": 1, "palabra": "olímpicamente-saqueo-sometido"}, {"valor": 1, "palabra": "saqueo-sometido-gobierno"}, {"valor": 1, "palabra": "sometido-gobierno-vaciado"}, {"valor": 1, "palabra": "gobierno-vaciado-embalses"}, {"valor": 1, "palabra": "vaciado-embalses-vendido"}, {"valor": 1, "palabra": "embalses-vendido-multinacionales"}, {"valor": 1, "palabra": "vendido-multinacionales-danone"}, {"valor": 1, "palabra": "multinacionales-danone-heineken"}, {"valor": 1, "palabra": "danone-heineken-schweppesnos"}, {"valor": 1, "palabra": "heineken-schweppesnos-vender"}, {"valor": 1, "palabra": "schweppesnos-vender-orosiendo"}, {"valor": 1, "palabra": "vender-orosiendo-nosotrosy"}, {"valor": 1, "palabra": "orosiendo-nosotrosy-prohibirán"}, {"valor": 1, "palabra": "nosotrosy-prohibirán-bañarn"}, {"valor": 1, "palabra": "prohibirán-bañarn-quieres"}, {"valor": 1, "palabra": "bañarn-quieres-galleta"}, {"valor": 1, "palabra": "quieres-galleta-comienza"}, {"valor": 1, "palabra": "galleta-comienza-amistad"}, {"valor": 1, "palabra": "comienza-amistad-verdad"}, {"valor": 1, "palabra": "amistad-verdad-nuestros"}, {"valor": 1, "palabra": "verdad-nuestros-supermercados"}, {"valor": 1, "palabra": "nuestros-supermercados-también"}, {"valor": 1, "palabra": "supermercados-también-aunque"}, {"valor": 1, "palabra": "también-aunque-olvide"}, {"valor": 1, "palabra": "aunque-olvide-comprensible"}, {"valor": 1, "palabra": "olvide-comprensible-caterva"}, {"valor": 1, "palabra": "comprensible-caterva-desneuronados"}, {"valor": 1, "palabra": "caterva-desneuronados-defiendan"}, {"valor": 1, "palabra": "desneuronados-defiendan-poderosa"}], "ARG - DANONE - LECHES DE FÓRMULA": [{"valor": 1, "palabra": "bautista-nutrilon-probamos"}, {"valor": 1, "palabra": "nutrilon-probamos-nidina"}, {"valor": 1, "palabra": "probamos-nidina-quiere"}, {"valor": 1, "palabra": "nidina-quiere-nadaaa"}], "ARG - DANONE - ETIQUETADO FRONTAL": [], "ARG - DANONE - MONITOREO EMERGENTE": []}}